gyt_cli/__init__.py
gyt_cli/cli.py
gyt_cli/constants.py
gyt_cli/utils.py
gyt_cli/commands/__init__.py
gyt_cli/commands/camp.py
gyt_cli/commands/ci.py
gyt_cli/commands/cleant.py
gyt_cli/commands/fresh.py
gyt_cli/commands/repo.py
gyt_cli/commands/conf/__init__.py
gyt_cli/commands/conf/aliases.py
gyt_cli/commands/conf/get.py
gyt_cli/commands/conf/init.py
gyt_cli/commands/conf/path.py
gyt_cli/commands/jira/__init__.py
gyt_cli/commands/jira/config.py
gyt_cli/commands/jira/open.py
gyt_cli/config/__init__.py
gyt_cli/config/model.py
gyt_cli-0.5.2.dist-info/METADATA
gyt_cli-0.5.2.dist-info/WHEEL
gyt_cli-0.5.2.dist-info/entry_points.txt
gyt_cli-0.5.2.dist-info/licenses/LICENSE
gyt_cli-0.5.2.dist-info/RECORD
