Metadata-Version: 2.4
Name: gyt-cli
Version: 0.5.2
Summary: A Python CLI abstracting common Git interactions like Conventional Commit and Atlassian Smart Commit helpers
Author-email: Nate Ferrell <nate@scrthq.com>
License-Expression: Apache-2.0
License-File: LICENSE
Requires-Python: <4.0.0,>=3.10
Requires-Dist: gitpython<4,>=3.1.43
Requires-Dist: pydantic<3,>=2.6.4
Requires-Dist: pyyaml<7,>=6.0.1
Requires-Dist: typer>=0.16.1
